devtimer/__init__.py
devtimer/__main__.py
pomodev-0.1.3.dist-info/licenses/LICENSE
pomodev-0.1.3.dist-info/METADATA
pomodev-0.1.3.dist-info/WHEEL
pomodev-0.1.3.dist-info/top_level.txt
pomodev-0.1.3.dist-info/RECORD
