Metadata-Version: 2.4
Name: pomodev
Version: 0.1.3
Summary: pomodoro timer for devs with git, streak and history
Author: Dhruv Tiwari
Author-email: Dhruv Tiwari <dhruv.d.tiwari@gmail.com>
License-Expression: MIT
Project-URL: Homepage, https://github.com/dhruv1710/pomodev
Project-URL: Issues, https://github.com/dhruv1710/pomodev/issues
Classifier: Programming Language :: Python :: 3
Classifier: Operating System :: OS Independent
Requires-Python: >=3.6
License-File: LICENSE
Dynamic: author
Dynamic: license-file
Dynamic: requires-python
